{"info": {"date_created": "2017/09/01", "contributor": "COCO Consortium", "year": 2017, "url": "http://cocodataset.org", "version": "1.0", "description": "COCO 2017 Dataset"}, "annotations": [{"area": 13008.645800000002, "id": 34867, "category_id": 72, "iscrowd": 0, "bbox": [269.2, 135.42, 119.75, 126.68], "segmentation": [[272.16, 135.42, 388.95, 146.31, 384.0, 262.1, 269.2, 243.3]], "image_id": 24104}, {"area": 291.5397499999996, "id": 1626513, "category_id": 72, "iscrowd": 0, "bbox": [235.19, 125.46, 16.71, 20.46], "segmentation": [[235.19, 145.92, 250.64, 144.67, 250.23, 134.23, 251.06, 130.05, 251.9, 129.22, 248.97, 127.13, 248.14, 126.29, 235.61, 125.46, 235.19, 144.67]], "image_id": 544968}, {"area": 7367.396050000003, "id": 28637, "category_id": 72, "iscrowd": 0, "bbox": [349.78, 178.22, 110.85, 78.57], "segmentation": [[349.78, 185.76, 452.02, 178.22, 460.63, 250.33, 367.0, 256.79, 359.46, 256.79]], "image_id": 210736}, {"area": 14627.805399999997, "id": 1624828, "category_id": 72, "iscrowd": 0, "bbox": [152.53, 63.15, 139.99, 123.74], "segmentation": [[166.98, 186.89, 292.52, 168.82, 288.46, 88.44, 283.94, 63.15, 152.53, 69.02]], "image_id": 544451}, {"area": 8033.319700000002, "id": 30888, "category_id": 72, "iscrowd": 0, "bbox": [0.0, 55.96, 108.7, 79.65], "segmentation": [[4.3, 130.22, 0.0, 55.96, 107.62, 59.19, 108.7, 131.3, 5.38, 135.61]], "image_id": 116147}, {"area": 1938.1908, "id": 1625255, "category_id": 72, "iscrowd": 0, "bbox": [64.6, 0.0, 68.96, 32.97], "segmentation": [[64.6, 0.6, 70.58, 32.97, 133.56, 28.04, 128.99, 0.0]], "image_id": 508477}, {"area": 10922.320549999997, "id": 35539, "category_id": 72, "iscrowd": 0, "bbox": [302.22, 61.83, 109.63, 118.52], "segmentation": [[302.22, 61.83, 411.85, 75.65, 407.9, 180.35, 303.21, 159.6, 302.22, 159.6]], "image_id": 484751}, {"area": 4615.154850000001, "id": 31848, "category_id": 72, "iscrowd": 0, "bbox": [276.0, 114.52, 77.35, 62.34], "segmentation": [[277.82, 114.98, 353.35, 117.25, 351.53, 176.86, 276.46, 176.4, 276.0, 114.52]], "image_id": 108254}, {"area": 8389.82335, "id": 34264, "category_id": 72, "iscrowd": 0, "bbox": [11.45, 152.88, 102.15, 112.73], "segmentation": [[17.61, 191.63, 21.14, 183.71, 40.51, 160.81, 90.71, 152.88, 100.4, 152.88, 110.96, 206.6, 108.32, 218.93, 113.6, 240.95, 101.28, 258.56, 73.09, 265.61, 48.44, 262.08, 42.27, 242.71, 26.42, 233.02, 11.45, 191.63]], "image_id": 141413}, {"area": 73906.75390000001, "id": 31901, "category_id": 72, "iscrowd": 0, "bbox": [1.08, 0.0, 442.33, 179.3], "segmentation": [[1.08, 161.0, 435.87, 179.3, 443.41, 173.92, 427.26, 0.0, 1.08, 0.0, 1.08, 157.78]], "image_id": 435882}], "images": [{"id": 24104, "height": 480, "coco_url": "http://images.cocodataset.org/train2017/000000024104.jpg", "width": 640, "file_name": "000000024104.jpg", "date_captured": "2013-11-22 01:13:45", "license": 1, "flickr_url": "http://farm4.staticflickr.com/3205/2614879210_eaa2ed45dd_z.jpg"}, {"id": 544968, "height": 427, "coco_url": "http://images.cocodataset.org/train2017/000000544968.jpg", "width": 640, "file_name": "000000544968.jpg", "date_captured": "2013-11-25 14:03:41", "license": 1, "flickr_url": "http://farm4.staticflickr.com/3777/10048309853_9250d4810e_z.jpg"}, {"id": 210736, "height": 480, "coco_url": "http://images.cocodataset.org/train2017/000000210736.jpg", "width": 640, "file_name": "000000210736.jpg", "date_captured": "2013-11-24 01:22:42", "license": 1, "flickr_url": "http://farm6.staticflickr.com/5211/5449084409_3c0304aaca_z.jpg"}, {"id": 544451, "height": 375, "coco_url": "http://images.cocodataset.org/train2017/000000544451.jpg", "width": 500, "file_name": "000000544451.jpg", "date_captured": "2013-11-22 00:46:57", "license": 4, "flickr_url": "http://farm1.staticflickr.com/22/37012274_e5dc2a0ecd_z.jpg"}, {"id": 116147, "height": 480, "coco_url": "http://images.cocodataset.org/train2017/000000116147.jpg", "width": 640, "file_name": "000000116147.jpg", "date_captured": "2013-11-21 20:26:54", "license": 3, "flickr_url": "http://farm7.staticflickr.com/6199/6114504472_631efc6a14_z.jpg"}, {"id": 508477, "height": 375, "coco_url": "http://images.cocodataset.org/train2017/000000508477.jpg", "width": 500, "file_name": "000000508477.jpg", "date_captured": "2013-11-17 19:00:31", "license": 5, "flickr_url": "http://farm4.staticflickr.com/3399/3276388216_1fd2868b68_z.jpg"}, {"id": 484751, "height": 480, "coco_url": "http://images.cocodataset.org/train2017/000000484751.jpg", "width": 640, "file_name": "000000484751.jpg", "date_captured": "2013-11-15 15:05:41", "license": 3, "flickr_url": "http://farm4.staticflickr.com/3462/3787509186_ed2e1892ab_z.jpg"}, {"id": 108254, "height": 360, "coco_url": "http://images.cocodataset.org/train2017/000000108254.jpg", "width": 640, "file_name": "000000108254.jpg", "date_captured": "2013-11-15 01:16:00", "license": 1, "flickr_url": "http://farm3.staticflickr.com/2664/4089396786_9019eee9ff_z.jpg"}, {"id": 141413, "height": 428, "coco_url": "http://images.cocodataset.org/train2017/000000141413.jpg", "width": 640, "file_name": "000000141413.jpg", "date_captured": "2013-11-21 19:54:18", "license": 1, "flickr_url": "http://farm4.staticflickr.com/3023/2829527880_2d53fdb8f6_z.jpg"}, {"id": 435882, "height": 480, "coco_url": "http://images.cocodataset.org/train2017/000000435882.jpg", "width": 640, "file_name": "000000435882.jpg", "date_captured": "2013-11-22 01:23:23", "license": 2, "flickr_url": "http://farm2.staticflickr.com/1427/921075074_1804ab16d4_z.jpg"}], "categories": [{"id": 1, "supercategory": "person", "name": "person"}, {"id": 2, "supercategory": "vehicle", "name": "bicycle"}, {"id": 3, "supercategory": "vehicle", "name": "car"}, {"id": 4, "supercategory": "vehicle", "name": "motorcycle"}, {"id": 5, "supercategory": "vehicle", "name": "airplane"}, {"id": 6, "supercategory": "vehicle", "name": "bus"}, {"id": 7, "supercategory": "vehicle", "name": "train"}, {"id": 8, "supercategory": "vehicle", "name": "truck"}, {"id": 9, "supercategory": "vehicle", "name": "boat"}, {"id": 10, "supercategory": "outdoor", "name": "traffic light"}, {"id": 11, "supercategory": "outdoor", "name": "fire hydrant"}, {"id": 13, "supercategory": "outdoor", "name": "stop sign"}, {"id": 14, "supercategory": "outdoor", "name": "parking meter"}, {"id": 15, "supercategory": "outdoor", "name": "bench"}, {"id": 16, "supercategory": "animal", "name": "bird"}, {"id": 17, "supercategory": "animal", "name": "cat"}, {"id": 18, "supercategory": "animal", "name": "dog"}, {"id": 19, "supercategory": "animal", "name": "horse"}, {"id": 20, "supercategory": "animal", "name": "sheep"}, {"id": 21, "supercategory": "animal", "name": "cow"}, {"id": 22, "supercategory": "animal", "name": "elephant"}, {"id": 23, "supercategory": "animal", "name": "bear"}, {"id": 24, "supercategory": "animal", "name": "zebra"}, {"id": 25, "supercategory": "animal", "name": "giraffe"}, {"id": 27, "supercategory": "accessory", "name": "backpack"}, {"id": 28, "supercategory": "accessory", "name": "umbrella"}, {"id": 31, "supercategory": "accessory", "name": "handbag"}, {"id": 32, "supercategory": "accessory", "name": "tie"}, {"id": 33, "supercategory": "accessory", "name": "suitcase"}, {"id": 34, "supercategory": "sports", "name": "frisbee"}, {"id": 35, "supercategory": "sports", "name": "skis"}, {"id": 36, "supercategory": "sports", "name": "snowboard"}, {"id": 37, "supercategory": "sports", "name": "sports ball"}, {"id": 38, "supercategory": "sports", "name": "kite"}, {"id": 39, "supercategory": "sports", "name": "baseball bat"}, {"id": 40, "supercategory": "sports", "name": "baseball glove"}, {"id": 41, "supercategory": "sports", "name": "skateboard"}, {"id": 42, "supercategory": "sports", "name": "surfboard"}, {"id": 43, "supercategory": "sports", "name": "tennis racket"}, {"id": 44, "supercategory": "kitchen", "name": "bottle"}, {"id": 46, "supercategory": "kitchen", "name": "wine glass"}, {"id": 47, "supercategory": "kitchen", "name": "cup"}, {"id": 48, "supercategory": "kitchen", "name": "fork"}, {"id": 49, "supercategory": "kitchen", "name": "knife"}, {"id": 50, "supercategory": "kitchen", "name": "spoon"}, {"id": 51, "supercategory": "kitchen", "name": "bowl"}, {"id": 52, "supercategory": "food", "name": "banana"}, {"id": 53, "supercategory": "food", "name": "apple"}, {"id": 54, "supercategory": "food", "name": "sandwich"}, {"id": 55, "supercategory": "food", "name": "orange"}, {"id": 56, "supercategory": "food", "name": "broccoli"}, {"id": 57, "supercategory": "food", "name": "carrot"}, {"id": 58, "supercategory": "food", "name": "hot dog"}, {"id": 59, "supercategory": "food", "name": "pizza"}, {"id": 60, "supercategory": "food", "name": "donut"}, {"id": 61, "supercategory": "food", "name": "cake"}, {"id": 62, "supercategory": "furniture", "name": "chair"}, {"id": 63, "supercategory": "furniture", "name": "couch"}, {"id": 64, "supercategory": "furniture", "name": "potted plant"}, {"id": 65, "supercategory": "furniture", "name": "bed"}, {"id": 67, "supercategory": "furniture", "name": "dining table"}, {"id": 70, "supercategory": "furniture", "name": "toilet"}, {"id": 72, "supercategory": "electronic", "name": "tv"}, {"id": 73, "supercategory": "electronic", "name": "laptop"}, {"id": 74, "supercategory": "electronic", "name": "mouse"}, {"id": 75, "supercategory": "electronic", "name": "remote"}, {"id": 76, "supercategory": "electronic", "name": "keyboard"}, {"id": 77, "supercategory": "electronic", "name": "cell phone"}, {"id": 78, "supercategory": "appliance", "name": "microwave"}, {"id": 79, "supercategory": "appliance", "name": "oven"}, {"id": 80, "supercategory": "appliance", "name": "toaster"}, {"id": 81, "supercategory": "appliance", "name": "sink"}, {"id": 82, "supercategory": "appliance", "name": "refrigerator"}, {"id": 84, "supercategory": "indoor", "name": "book"}, {"id": 85, "supercategory": "indoor", "name": "clock"}, {"id": 86, "supercategory": "indoor", "name": "vase"}, {"id": 87, "supercategory": "indoor", "name": "scissors"}, {"id": 88, "supercategory": "indoor", "name": "teddy bear"}, {"id": 89, "supercategory": "indoor", "name": "hair drier"}, {"id": 90, "supercategory": "indoor", "name": "toothbrush"}], "licenses": [{"url": "http://creativecommons.org/licenses/by-nc-sa/2.0/", "id": 1, "name": "Attribution-NonCommercial-ShareAlike License"}, {"url": "http://creativecommons.org/licenses/by-nc/2.0/", "id": 2, "name": "Attribution-NonCommercial License"}, {"url": "http://creativecommons.org/licenses/by-nc-nd/2.0/", "id": 3, "name": "Attribution-NonCommercial-NoDerivs License"}, {"url": "http://creativecommons.org/licenses/by/2.0/", "id": 4, "name": "Attribution License"}, {"url": "http://creativecommons.org/licenses/by-sa/2.0/", "id": 5, "name": "Attribution-ShareAlike License"}, {"url": "http://creativecommons.org/licenses/by-nd/2.0/", "id": 6, "name": "Attribution-NoDerivs License"}, {"url": "http://flickr.com/commons/usage/", "id": 7, "name": "No known copyright restrictions"}, {"url": "http://www.usa.gov/copyright.shtml", "id": 8, "name": "United States Government Work"}]}